adl2pydm/__init__.py
adl2pydm/_version.py
adl2pydm/adl_parser.py
adl2pydm/calc2rules.py
adl2pydm/cli.py
adl2pydm/output_handler.py
adl2pydm/symbols.py
adl2pydm/tests/__init__.py
adl2pydm/tests/_core.py
adl2pydm/tests/test_adl_parser.py
adl2pydm/tests/test_calc2rules.py
adl2pydm/tests/test_cli.py
adl2pydm/tests/test_issue61.py
adl2pydm/tests/test_output_handler.py
adl2pydm/tests/test_simple.py
adl2pydm/tests/test_symbols.py
adl2pydm/tests/test_testDisplay.py
adl2pydm/tests/test_trouble_screens.py
pyqtdesignerpath/pydm_designer_plugin.py
adl2pydm-0.0.4.dist-info/LICENSE.txt
adl2pydm-0.0.4.dist-info/METADATA
adl2pydm-0.0.4.dist-info/WHEEL
adl2pydm-0.0.4.dist-info/entry_points.txt
adl2pydm-0.0.4.dist-info/top_level.txt
adl2pydm-0.0.4.dist-info/RECORD
